LICENSE
MANIFEST.in
README.md
setup.cfg
setup.py
versioneer.py
pmx/__init__.py
pmx/__init__.pyc
pmx/_version.py
pmx/atom.py
pmx/atom.pyc
pmx/atomselection.py
pmx/builder.py
pmx/chain.py
pmx/cpp.py
pmx/estimators.py
pmx/ffparser.py
pmx/forcefield.py
pmx/forcefield2.py
pmx/futil.py
pmx/geometry.py
pmx/histogram.py
pmx/library.py
pmx/model.py
pmx/molecule.py
pmx/mutdb.py
pmx/ndx.py
pmx/odict.py
pmx/options.py
pmx/parser.py
pmx/rotamer.py
pmx/tCNC.py
pmx/xdrfile.py
pmx/xtc.py
pmx.egg-info/PKG-INFO
pmx.egg-info/SOURCES.txt
pmx.egg-info/dependency_links.txt
pmx.egg-info/entry_points.txt
pmx.egg-info/not-zip-safe
pmx.egg-info/requires.txt
pmx.egg-info/top_level.txt
pmx/data/bbdep.pkl
pmx/data/blosum62_new.mat
pmx/data/bp.pkl
pmx/data/bp_amber.pkl
pmx/data/bp_charmm.pkl
pmx/data/ffamber99sb.rtp
pmx/data/ffamber99sbbon.itp
pmx/data/ffamber99sbnb.itp
pmx/data/rna.pkl
pmx/data/mutff/ffamber99sb-c.tdb
pmx/data/mutff/ffamber99sb-n.tdb
pmx/data/mutff/ffamber99sb.atp
pmx/data/mutff/ffamber99sb.hdb
pmx/data/mutff/ffamber99sb.itp
pmx/data/mutff/ffamber99sb.mtp
pmx/data/mutff/ffamber99sb.rtp
pmx/data/mutff/ffamber99sbbon.itp
pmx/data/mutff/ffamber99sbnb.itp
pmx/data/mutff/ions.itp
pmx/data/mutff/spce.itp
pmx/data/mutff/tip3p.gro
pmx/data/mutff/tip3p.itp
pmx/data/mutff45/atommass.dat
pmx/data/mutff45/elements.dat
pmx/data/mutff45/residuetypes.dat
pmx/data/mutff45/spc216.gro
pmx/data/mutff45/specbond.dat
pmx/data/mutff45/vdwradii.dat
pmx/data/mutff45/xlateat.dat
pmx/data/mutff45/amber99sb-star-ildn-mut.ff/aminoacids.arn
pmx/data/mutff45/amber99sb-star-ildn-mut.ff/aminoacids.c.tdb
pmx/data/mutff45/amber99sb-star-ildn-mut.ff/aminoacids.hdb
pmx/data/mutff45/amber99sb-star-ildn-mut.ff/aminoacids.n.tdb
pmx/data/mutff45/amber99sb-star-ildn-mut.ff/aminoacids.r2b
pmx/data/mutff45/amber99sb-star-ildn-mut.ff/aminoacids.rtp
pmx/data/mutff45/amber99sb-star-ildn-mut.ff/aminoacids.vsd
pmx/data/mutff45/amber99sb-star-ildn-mut.ff/atomtypes.atp
pmx/data/mutff45/amber99sb-star-ildn-mut.ff/backup_mutres
pmx/data/mutff45/amber99sb-star-ildn-mut.ff/dna.arn
pmx/data/mutff45/amber99sb-star-ildn-mut.ff/dna.hdb
pmx/data/mutff45/amber99sb-star-ildn-mut.ff/dna.r2b
