Metadata-Version: 1.2
Name: pmx
Version: 2.0
Summary: Python Toolbox structure file editing and writing simulation setup/analysis tools
Home-page: https://github.com/deGrootLab/pmx
Author: Daniel Seeliger
Author-email: seeliger.biosoft@gmail.de
License: GPL 3
Download-URL: https://github.com/deGrootLab/pmx/releases/latest
Platform: UNKNOWN
Classifier: Development Status :: 5 - Production/Stable
Classifier: License :: OSI Approved :: GNU General Public License (GPL)
Classifier: Programming Language :: Python
Classifier: Intended Audience :: Science/Research
Classifier: Topic :: Scientific/Engineering
Requires-Python: >=2.7, <3
